{
  "generated_at": "2026-04-21 11:34 CT",
  "generated_ts": "2026-04-21T11:34:54.611369-05:00",
  "session_name": "DEAD ZONE",
  "session_trade": false,
  "session_advice": "No new entries. Theta bleeds.",
  "market": {
    "price": 200.03,
    "prev_close": 202.06,
    "change": -2.03,
    "change_pct": -1.0,
    "volume": 52321616,
    "avg_vol": 175294618,
    "vol_ratio": 0.3,
    "vol_20ma": 151.3,
    "week52h": 212.19,
    "week52l": 97.28,
    "atr": 4.48,
    "compression": 9.2,
    "id_high": 202.75,
    "id_low": 197.84
  },
  "spy": {
    "price": 706.9,
    "e50": 676.99,
    "bull": true
  },
  "signals": {
    "ichimoku": {
      "bull": false,
      "bear": false,
      "label": "WEAK BEAR",
      "detail": "Below cloud, T\u2265K",
      "tenkan": 200.96,
      "kijun": 200.94,
      "cloud_top": 200.95,
      "cloud_bottom": 200.29
    },
    "kama": {
      "bull": "True",
      "bear": "False",
      "label": "BULL",
      "detail": "HLC3>200.0 \u00b7 KAMA\u2191 \u00b7 ER0.63",
      "kama_val": 199.95,
      "er": 0.635
    },
    "rsi": {
      "bull": false,
      "bear": false,
      "label": "MID",
      "detail": "RSI 51 \u00b7 wait 45/55",
      "rsi_val": 50.8,
      "rsi_prev": 46.2
    },
    "macd_combo": {
      "bull": false,
      "bear": false,
      "label": "WAIT",
      "detail": "MACD -0.342 \u00b7 RSI51",
      "macd_h": -0.342,
      "rsi_val": 50.8
    },
    "divergence": {
      "divergence_type": null,
      "label": "None",
      "detail": "",
      "strength": null,
      "confirms_bull": false,
      "confirms_bear": false,
      "exit_warning_bull": false,
      "exit_warning_bear": false
    }
  },
  "timeframes": {
    "daily": {
      "label": "DAILY",
      "e8": 196.29,
      "e21": 188.7,
      "e50": 185.18,
      "rsi": 91.7,
      "macd_h": 2.536,
      "macd_h_prev": 2.907,
      "vol_ratio": 0.35,
      "hh_hl": false,
      "above_cloud": true,
      "below_cloud": false,
      "fast_bull": true,
      "macd_bull": true,
      "macd_turning": false,
      "macd_turning_bear": false,
      "rsi_expansion_bull": true,
      "rsi_expansion_bear": false,
      "vol_expanded": false,
      "rsi_above_50": true
    },
    "h4": {
      "label": "4H",
      "e8": 199.07,
      "e21": 193.0,
      "e50": 186.85,
      "rsi": 76.5,
      "macd_h": 0.477,
      "macd_h_prev": 0.772,
      "vol_ratio": 0.84,
      "hh_hl": false,
      "above_cloud": true,
      "below_cloud": false,
      "fast_bull": true,
      "macd_bull": true,
      "macd_turning": false,
      "macd_turning_bear": false,
      "rsi_expansion_bull": true,
      "rsi_expansion_bear": false,
      "vol_expanded": false,
      "rsi_above_50": true
    },
    "h1": {
      "label": "1H",
      "e8": 200.56,
      "e21": 199.78,
      "e50": 195.93,
      "rsi": 50.8,
      "macd_h": -0.342,
      "macd_h_prev": -0.291,
      "vol_ratio": 0.05,
      "hh_hl": false,
      "above_cloud": true,
      "below_cloud": false,
      "fast_bull": true,
      "macd_bull": false,
      "macd_turning": false,
      "macd_turning_bear": false,
      "rsi_expansion_bull": false,
      "rsi_expansion_bear": false,
      "vol_expanded": false,
      "rsi_above_50": true
    },
    "m15": {
      "label": "15M",
      "e8": 200.61,
      "e21": 200.77,
      "e50": 200.4,
      "rsi": 36.4,
      "macd_h": -0.225,
      "macd_h_prev": -0.205,
      "vol_ratio": 0.2,
      "hh_hl": false,
      "above_cloud": false,
      "below_cloud": true,
      "fast_bull": false,
      "macd_bull": false,
      "macd_turning": false,
      "macd_turning_bear": false,
      "rsi_expansion_bull": false,
      "rsi_expansion_bear": true,
      "vol_expanded": false,
      "rsi_above_50": false
    }
  },
  "brando": {
    "res": [
      {
        "price": 200.08,
        "tf": "WK",
        "label": "KEY WALL $200",
        "key": true
      },
      {
        "price": 200.6,
        "tf": "DY",
        "label": "RESISTANCE",
        "key": false
      },
      {
        "price": 212.32,
        "tf": "WK",
        "label": "PRIOR ATH ZONE",
        "key": true
      },
      {
        "price": 225.0,
        "tf": "MO",
        "label": "MAJOR RESISTANCE",
        "key": false
      },
      {
        "price": 225.3,
        "tf": "WK",
        "label": "MAJOR RESISTANCE",
        "key": false
      },
      {
        "price": 250.0,
        "tf": "WK",
        "label": "RESISTANCE",
        "key": false
      }
    ],
    "sup": [
      {
        "price": 200.0,
        "tf": "MO",
        "label": "KEY WALL $200",
        "key": true
      },
      {
        "price": 196.05,
        "tf": "DY",
        "label": "RESISTANCE",
        "key": false
      },
      {
        "price": 191.0,
        "tf": "MO",
        "label": "YELLOW LINE $191",
        "key": true
      },
      {
        "price": 190.4,
        "tf": "DY",
        "label": "RESISTANCE",
        "key": false
      },
      {
        "price": 184.58,
        "tf": "DY",
        "label": "KEY RESISTANCE",
        "key": true
      },
      {
        "price": 180.34,
        "tf": "DY",
        "label": "CRITICAL PIVOT",
        "key": true
      }
    ],
    "key_res": {
      "price": 200.08,
      "tf": "WK",
      "label": "KEY WALL $200",
      "key": true
    },
    "key_sup": {
      "price": 200.0,
      "tf": "MO",
      "label": "KEY WALL $200",
      "key": true
    },
    "nearest": {
      "price": 200.0,
      "tf": "MO",
      "label": "KEY WALL $200",
      "key": true
    },
    "on_level": true,
    "scen_label": "ABOVE $200 WALL",
    "scen_color": "bull",
    "scen_a": "Hold calls. Target $212 then $225. Trail stop $196.",
    "scen_b": "Rejection $200\u2013$212 \u2192 take profits."
  },
  "options": {
    "expiry": "2026-05-22",
    "dte": 31,
    "iv_30": 43.3,
    "exp_move": 25.24,
    "calls": [
      {
        "strike": 185.0,
        "price": 20.15,
        "bid": 19.85,
        "ask": 20.2,
        "iv": 48.9,
        "volume": 353,
        "oi": 3420
      },
      {
        "strike": 190.0,
        "price": 16.58,
        "bid": 16.3,
        "ask": 16.55,
        "iv": 46.9,
        "volume": 91,
        "oi": 8468
      },
      {
        "strike": 195.0,
        "price": 13.26,
        "bid": 13.0,
        "ask": 13.25,
        "iv": 45.2,
        "volume": 1081,
        "oi": 4508
      },
      {
        "strike": 200.0,
        "price": 10.2,
        "bid": 10.1,
        "ask": 10.25,
        "iv": 43.3,
        "volume": 1048,
        "oi": 14514
      },
      {
        "strike": 205.0,
        "price": 7.8,
        "bid": 7.75,
        "ask": 7.85,
        "iv": 42.4,
        "volume": 6224,
        "oi": 8636
      },
      {
        "strike": 210.0,
        "price": 5.9,
        "bid": 5.7,
        "ask": 5.85,
        "iv": 41.6,
        "volume": 578,
        "oi": 6185
      },
      {
        "strike": 215.0,
        "price": 4.2,
        "bid": 4.1,
        "ask": 4.25,
        "iv": 40.8,
        "volume": 610,
        "oi": 10771
      },
      {
        "strike": 220.0,
        "price": 2.93,
        "bid": 2.9,
        "ask": 2.99,
        "iv": 40.1,
        "volume": 484,
        "oi": 8463
      }
    ],
    "puts": [
      {
        "strike": 220.0,
        "price": 20.55,
        "bid": 21.3,
        "ask": 21.75,
        "iv": 33.0,
        "volume": 61,
        "oi": 179
      },
      {
        "strike": 215.0,
        "price": 17.3,
        "bid": 17.8,
        "ask": 18.25,
        "iv": 36.0,
        "volume": 4,
        "oi": 44
      },
      {
        "strike": 210.0,
        "price": 14.05,
        "bid": 14.45,
        "ask": 14.7,
        "iv": 36.5,
        "volume": 22,
        "oi": 261
      },
      {
        "strike": 205.0,
        "price": 11.5,
        "bid": 11.5,
        "ask": 11.7,
        "iv": 37.7,
        "volume": 99,
        "oi": 462
      },
      {
        "strike": 200.0,
        "price": 9.0,
        "bid": 9.0,
        "ask": 9.15,
        "iv": 38.8,
        "volume": 370,
        "oi": 1628
      },
      {
        "strike": 195.0,
        "price": 6.85,
        "bid": 6.95,
        "ask": 7.05,
        "iv": 40.1,
        "volume": 128,
        "oi": 2314
      },
      {
        "strike": 190.0,
        "price": 5.1,
        "bid": 5.2,
        "ask": 5.35,
        "iv": 41.5,
        "volume": 437,
        "oi": 3214
      },
      {
        "strike": 185.0,
        "price": 3.8,
        "bid": 3.85,
        "ask": 3.95,
        "iv": 42.6,
        "volume": 432,
        "oi": 5926
      }
    ],
    "iv_stats": {
      "iv_rank": 81.5,
      "iv_pct": 92.7,
      "hv_20": 33.2,
      "iv_vs_hv": 10.1,
      "iv_quality": "High IV \u2014 overpaying, consider waiting"
    },
    "call_analytics": {
      "strike": 205.0,
      "premium": 7.8,
      "bid": 7.75,
      "ask": 7.85,
      "iv": 42.4,
      "volume": 6224,
      "oi": 8636,
      "breakeven": 212.8,
      "move_to_be": 12.77,
      "move_to_be_pct": 6.38,
      "approx_delta": 0.38,
      "daily_theta": 0.238,
      "days_to_danger": 10,
      "move_for_2x": 20.53,
      "move_for_2x_pct": 10.26,
      "max_loss": 780.0,
      "spread": 0.1,
      "liq": "Tight",
      "target_prem": 14.04,
      "stop_prem": 3.9,
      "exit_pct": 80,
      "stop_pct": 50
    },
    "put_analytics": {
      "strike": 195.0,
      "premium": 6.85,
      "bid": 6.95,
      "ask": 7.05,
      "iv": 40.1,
      "volume": 128,
      "oi": 2314,
      "breakeven": 188.15,
      "move_to_be": 11.88,
      "move_to_be_pct": 5.94,
      "approx_delta": 0.37,
      "daily_theta": 0.197,
      "days_to_danger": 10,
      "move_for_2x": 18.51,
      "move_for_2x_pct": 9.25,
      "max_loss": 685.0,
      "spread": 0.1,
      "liq": "Low volume",
      "target_prem": 12.33,
      "stop_prem": 3.42,
      "exit_pct": 80,
      "stop_pct": 50
    }
  },
  "news": [
    {
      "title": "UnitedHealth Group Surprises Wall Street. Is It Time to Load Up on the Beaten-Down Buffett Stock?",
      "published": "Tue, 21 Apr 2026 16:23",
      "link": "https://www.fool.com/investing/2026/04/21/unitedhealth-group-surprises-wall-street-is-it-tim/?.tsrc=rss",
      "sentiment": "neut"
    },
    {
      "title": "Apple vs. Microsoft: What's the Better \"Magnificent Seven\" Stock to Buy in 2026?",
      "published": "Tue, 21 Apr 2026 16:20",
      "link": "https://www.fool.com/investing/2026/04/21/apple-vs-microsoft-whats-the-better-magnificient-s/?.tsrc=rss",
      "sentiment": "bull"
    },
    {
      "title": "Nvidia Stock-Split: 2 Years and $1.5 Trillion Later, Can It Reach $1,200 Again?",
      "published": "Tue, 21 Apr 2026 16:10",
      "link": "https://www.fool.com/investing/2026/04/21/nvidia-stock-1200-price-target-timeline/?.tsrc=rss",
      "sentiment": "neut"
    },
    {
      "title": "Why Palo Alto Networks Stock Popped Today",
      "published": "Tue, 21 Apr 2026 16:09",
      "link": "https://www.fool.com/investing/2026/04/21/why-palo-alto-networks-stock-popped-today/?.tsrc=rss",
      "sentiment": "neut"
    },
    {
      "title": "Forget (XRP) Ripple: This Cryptocurrency Has A Real Moat",
      "published": "Tue, 21 Apr 2026 16:04",
      "link": "https://www.fool.com/investing/2026/04/21/forget-xrp-ripple-this-cryptocurrency-has-a-real-m/?.tsrc=rss",
      "sentiment": "neut"
    }
  ],
  "alignment": {
    "call_count": 1,
    "put_count": 0,
    "max_signals": 4,
    "call_reasons": [
      {
        "text": "S1 ICHI: Below cloud, T\u2265K",
        "pass": false
      },
      {
        "text": "S2 KAMA: HLC3>200.0 \u00b7 KAMA\u2191 \u00b7 ER0.63",
        "pass": true
      },
      {
        "text": "S3 RSI: RSI 51 \u00b7 wait 45/55",
        "pass": false
      },
      {
        "text": "S4 MACD: MACD -0.342 \u00b7 RSI51",
        "pass": false
      }
    ],
    "put_reasons": [
      {
        "text": "S1 ICHI: Below cloud, T\u2265K",
        "pass": false
      },
      {
        "text": "S2 KAMA: HLC3>200.0 \u00b7 KAMA\u2191 \u00b7 ER0.63",
        "pass": false
      },
      {
        "text": "S3 RSI: RSI 51 \u00b7 wait 45/55",
        "pass": false
      },
      {
        "text": "S4 MACD: MACD -0.342 \u00b7 RSI51",
        "pass": false
      }
    ],
    "call_context": [
      {
        "text": "Brando pivot $180.34 \u2014 above",
        "pass": true
      },
      {
        "text": "SPY vs 50 EMA \u2014 tailwind",
        "pass": true
      },
      {
        "text": "Vol 0.3x \u2014 low-vol pullback",
        "pass": true
      },
      {
        "text": "Session: DEAD ZONE",
        "pass": false
      }
    ],
    "put_context": [
      {
        "text": "Brando pivot $180.34 \u2014 above",
        "pass": false
      },
      {
        "text": "SPY vs 50 EMA \u2014 headwind",
        "pass": false
      },
      {
        "text": "Vol 0.3x \u2014 low-vol decline (dead cat)",
        "pass": false
      },
      {
        "text": "Session: DEAD ZONE",
        "pass": false
      }
    ],
    "h1_div": {
      "divergence_type": null,
      "label": "None",
      "detail": "",
      "strength": null,
      "confirms_bull": false,
      "confirms_bear": false,
      "exit_warning_bull": false,
      "exit_warning_bear": false
    }
  },
  "verdict": {
    "verdict": "DEAD ZONE \u2014 NO TRADES",
    "bias": "WAIT",
    "explanation": "No new entries. Theta bleeds.",
    "trade_idea": "Next: Power Window 1:00 PM CT.",
    "level": "none"
  },
  "candles": [
    {
      "time": "10:55 AM",
      "open": 200.85,
      "high": 201.06,
      "low": 200.67,
      "close": 200.72,
      "volume": 921981,
      "bull": false
    },
    {
      "time": "11:00 AM",
      "open": 200.73,
      "high": 200.89,
      "low": 200.31,
      "close": 200.5,
      "volume": 1556287,
      "bull": false
    },
    {
      "time": "11:05 AM",
      "open": 200.51,
      "high": 200.66,
      "low": 200.35,
      "close": 200.62,
      "volume": 834294,
      "bull": true
    },
    {
      "time": "11:10 AM",
      "open": 200.63,
      "high": 200.65,
      "low": 200.23,
      "close": 200.39,
      "volume": 797845,
      "bull": false
    },
    {
      "time": "11:15 AM",
      "open": 200.38,
      "high": 200.56,
      "low": 200.33,
      "close": 200.4,
      "volume": 796422,
      "bull": true
    },
    {
      "time": "11:20 AM",
      "open": 200.4,
      "high": 200.4,
      "low": 200.04,
      "close": 200.1,
      "volume": 1011824,
      "bull": false
    },
    {
      "time": "11:25 AM",
      "open": 200.1,
      "high": 200.18,
      "low": 199.87,
      "close": 199.9,
      "volume": 1309710,
      "bull": false
    },
    {
      "time": "11:30 AM",
      "open": 199.89,
      "high": 200.15,
      "low": 199.88,
      "close": 200.04,
      "volume": 775763,
      "bull": true
    }
  ]
}